ncloud_monitoring/__init__.py
ncloud_monitoring/api_client.py
ncloud_monitoring/configuration.py
ncloud_monitoring/rest.py
ncloud_monitoring/api/__init__.py
ncloud_monitoring/api/v2_api.py
ncloud_monitoring/model/__init__.py
ncloud_monitoring/model/data_point.py
ncloud_monitoring/model/get_list_metrics_request.py
ncloud_monitoring/model/get_list_metrics_response.py
ncloud_monitoring/model/get_metric_statistic_list_request.py
ncloud_monitoring/model/get_metric_statistic_list_response.py
ncloud_monitoring/model/metric.py
ncloud_monitoring/model/metric_data.py
ncloud_monitoring/model/metric_statistic.py
test/__init__.py
test/test_v2_api.py
ncloud_monitoring-1.1.6.dist-info/LICENSE
ncloud_monitoring-1.1.6.dist-info/METADATA
ncloud_monitoring-1.1.6.dist-info/WHEEL
ncloud_monitoring-1.1.6.dist-info/top_level.txt
ncloud_monitoring-1.1.6.dist-info/RECORD
