Metadata-Version: 1.0
Name: ncloud-monitoring
Version: 1.1.6
Summary: monitoring
Home-page: UNKNOWN
Author: UNKNOWN
Author-email: UNKNOWN
License: UNKNOWN
Keywords: monitoring
Platform: UNKNOWN
